fritzremote/__init__.py
fritzremote/fritzremote.py
fritzremote/model.py
fritzremote-0.0.1.dist-info/LICENSE
fritzremote-0.0.1.dist-info/METADATA
fritzremote-0.0.1.dist-info/WHEEL
fritzremote-0.0.1.dist-info/top_level.txt
fritzremote-0.0.1.dist-info/RECORD
