Metadata-Version: 2.1
Name: fritzremote
Version: 0.0.1
Summary: Let's you remote your Fritz!Box via selenium
Home-page: https://github.com/dennisschroeder/fritzremote
Author: Dennis Schroeder
Author-email: dennisschroeder@me.com
License: MIT
Platform: UNKNOWN
Classifier: Programming Language :: Python :: 3.7
Classifier: License :: OSI Approved :: MIT License
Classifier: Operating System :: OS Independent
Requires-Dist: selenium
